barsup_core-0.2.9.dist-info/RECORD
barsup_core-0.2.9.dist-info/WHEEL
barsup_core-0.2.9.dist-info/metadata.json
barsup_core-0.2.9.dist-info/DESCRIPTION.rst
barsup_core-0.2.9.dist-info/METADATA
barsup_core-0.2.9.dist-info/top_level.txt
barsup_core-0.2.9.data/scripts/bup_cli
barsup_core-0.2.9.data/scripts/bup_manage
barsup/wsgi.py
barsup/util.py
barsup/session.py
barsup/service.py
barsup/schema.py
barsup/router.py
barsup/middleware.py
barsup/manage.py
barsup/exceptions.py
barsup/core.py
barsup/controller.py
barsup/cli.py
barsup/adapter.py
barsup/accli.py
barsup/__init__.py
barsup/tests/test_util.py
barsup/tests/test_router.py
barsup/tests/test_modules_w_context.py
barsup/tests/test_module_container.py
barsup/tests/test_middleware.py
barsup/tests/test_core.py
barsup/tests/test_controller.py
barsup/tests/__init__.py
barsup/tests/wsgi/test_wsgi.py
barsup/tests/wsgi/__init__.py
barsup/tests/cli/test_cli.py
barsup/tests/cli/test_accli.py
barsup/tests/cli/__init__.py
barsup/tests/auth/test_auth_for_moduling.py
barsup/tests/auth/test_auth.py
barsup/tests/auth/__init__.py
barsup/tests/api/test_api.py
barsup/tests/api/__init__.py
barsup/auth/util.py
barsup/auth/service.py
barsup/auth/middleware.py
barsup/auth/management.py
barsup/auth/controller.py
barsup/auth/adapter.py
barsup/auth/__init__.py
