Metadata-Version: 2.0
Name: barsup-core
Version: 0.2.9
Summary: UNKNOWN
Home-page: https://bitbucket.org/barsgroup/barsup-core
Author: Telepenin Nikolay, Aleksey Pirogov
Author-email: telepenin@bars-open.ru,pirogov@bars-open.ru
License: MIT
Platform: UNKNOWN
Classifier: Intended Audience :: Developers
Classifier: Environment :: Web Environment
Classifier: Natural Language :: Russian
Classifier: Natural Language :: English
Classifier: Operating System :: OS Independent
Classifier: Programming Language :: Python
Classifier: License :: OSI Approved :: MIT License
Classifier: Development Status :: 4 - Beta
Classifier: Programming Language :: Python :: 3.3
Classifier: Programming Language :: Python :: 3.4
Classifier: Programming Language :: Python :: Implementation :: CPython
Requires-Dist: sqlalchemy
Requires-Dist: psycopg2
Requires-Dist: Routes
Requires-Dist: python-dateutil
Requires-Dist: alembic
Requires-Dist: simplejson
Requires-Dist: yadic
Requires-Dist: webob
